Workbook

Sheet README
A1: INFOSYS 3-STATEMENT FINANCIAL MODEL
A3: PROJECT OVERVIEW
A4: Purpose | B4: Three-statement financial model for Infosys using historical FY2025-FY2026 consolidated financials and FY2027-FY2029 forecast assumptions.
A5: Company | B5: Infosys Limited
A6: Financial Statements | B6: Income Statement, Balance Sheet, Cash Flow Statement
A7: Historical Period | B7: FY2025-FY2026
A8: Forecast Period | B8: FY2027-FY2029
A9: Currency / Units | B9: ₹ crore
A11: MODEL STRUCTURE
A12: Assumptions | B12: Forecast drivers and operating assumptions
A13: Income Statement | B13: Historical and forecast profitability
A14: Balance Sheet | B14: Historical and forecast financial position
A15: Cash Flow Statement | B15: Historical and forecast cash generation
A16: 3-Statement Model | B16: Integrated three-statement forecast
A17: Analysis | B17: Financial ratios and model checks
A19: KEY FORECAST ASSUMPTIONS
A20: Revenue Growth | B20: 0.08
A21: Other Income / Revenue | B21: 0.024
A22: Employee Expenses / Revenue | B22: 0.532
A23: Other Operating Expenses / Revenue | B23: 0.225
A24: Depreciation / Revenue | B24: 0.027
A25: Finance Cost / Revenue | B25: 0.002
A26: Tax Rate | B26: 0.263
A27: Capital Expenditure / Revenue | B27: 0.015
A28: Trade Receivables / Revenue | B28: 0.197
A29: Trade Payables / Revenue | B29: 0.027
A30: Dividend Payout Ratio | B30: 0.63
A32: MODEL LIMITATIONS
A33: 1. Forecasts are model estimates, not Infosys management guidance.
A34: 2. Forecast assumptions are simplified and remain constant across the forecast period.
A35: 3. Several Balance Sheet and Cash Flow items are projected using historical ratios or simplified assumptions.
A36: 4. The Balance Sheet reconciliation adjustment is a modeling mechanism used to integrate the three statements.
A37: 5. Detailed taxes, working-capital drivers, acquisitions, buybacks, and investment flows are simplified in the forecast.
A38: 6. Historical financial statements use consolidated Infosys figures reported in the FY2025-26 Annual Report.
A40: SOURCE
A41: Infosys Integrated Annual Report FY2025-26 — Consolidated Financial Statements

Sheet Assumptions
A1: INFOSYS FORECAST ASSUMPTIONS
A3: Assumption | B3: FY2027 | C3: FY2028 | D3: FY2029
A4: Revenue growth | B4: 0.08 | C4: 0.08 | D4: 0.08
A5: Other income / Revenue | B5: 0.024 | C5: 0.024 | D5: 0.024
A6: Employee expenses / Revenue | B6: 0.532 | C6: 0.532 | D6: 0.532
A7: Other operating expenses / Revenue | B7: 0.225 | C7: 0.225 | D7: 0.225
A8: Depreciation / Revenue | B8: 0.027 | C8: 0.027 | D8: 0.027
A9: Finance cost / Revenue | B9: 0.002 | C9: 0.002 | D9: 0.002
A10: Tax rate | B10: 0.263 | C10: 0.263 | D10: 0.263
A11: Capital expenditure / Revenue | B11: 0.015 | C11: 0.015 | D11: 0.015
A12: Trade receivables / Revenue | B12: 0.197 | C12: 0.197 | D12: 0.197
A13: Trade payables / Revenue | B13: 0.027 | C13: 0.027 | D13: 0.027
A14: Dividend payout ratio | B14: 0.63 | C14: 0.63 | D14: 0.63

Sheet Income Statement
A1: INFOSYS CONSOLIDATED INCOME STATEMENT
A3: Particulars | B3: FY2026 | C3: FY2025 | D3: Growth %
A4: Revenue from operations | B4: 178650 | C4: 162990 | D4: =(B4/C4)-1 -> 0.096079514
A5: Other income, net | B5: 4322 | C5: 3600 | D5: =(B5/C5)-1 -> 0.20055556
A6: Total income | B6: 182972 | C6: 166590 | D6: =(B6/C6)-1 -> 0.098337235
A7: Employee benefit expenses | B7: 95094 | C7: 85950 | D7: =(B7/C7)-1 -> 0.10638743
A8: Cost of technical sub-contractors | B8: 15421 | C8: 12937 | D8: =(B8/C8)-1 -> 0.19200742
A9: Travel expenses | B9: 2097 | C9: 1894 | D9: =(B9/C9)-1 -> 0.10718057
A10: Cost of software packages and others | B10: 15722 | C10: 15911 | D10: =(B10/C10)-1 -> -0.011878575
A11: Communication expenses | B11: 603 | C11: 620 | D11: =(B11/C11)-1 -> -0.027419355
A12: Consultancy and professional charges | B12: 2090 | C12: 1655 | D12: =(B12/C12)-1 -> 0.26283988
A13: Depreciation and amortization expenses | B13: 4902 | C13: 4812 | D13: =(B13/C13)-1 -> 0.018703242
A14: Finance cost | B14: 416 | C14: 416 | D14: =(B14/C14)-1 -> 0
A15: Other expenses | B15: 5343 | C15: 4787 | D15: =(B15/C15)-1 -> 0.1161479
... A17: Profit before exceptional item and tax | B17: 41284 | C17: 37608 | D17: =(B17/C17)-1 -> 0.097745161
A18: Exceptional item | B18: 1289 | C18: 0 | D18: ="N/A" -> N/A
A19: Profit before tax | B19: 39995 | C19: 37608 | D19: =(B19/C19)-1 -> 0.063470538
A20: Current tax | B20: 11767 | C20: 12130 | D20: =(B20/C20)-1 -> -0.029925804
A21: Deferred tax | B21: -1246 | C21: -1272 | D21: =(B21/C21)-1 -> -0.020440252
A22: Profit for the year | B22: 29474 | C22: 26750 | D22: =(B22/C22)-1 -> 0.10183178

Sheet Balance Sheet
A1: INFOSYS CONSOLIDATED BALANCE SHEET
A3: Particulars | B3: FY2026 | C3: FY2025 | D3: Growth %
A4: Property, plant and equipment | B4: 12651 | C4: 11778 | D4: =(B4/C4)-1 -> 0.074121243
A5: Right-of-use assets | B5: 6177 | C5: 6311 | D5: =(B5/C5)-1 -> -0.021232768
A6: Capital work-in-progress | B6: 526 | C6: 814 | D6: =(B6/C6)-1 -> -0.35380835
A7: Goodwill | B7: 12117 | C7: 10106 | D7: =(B7/C7)-1 -> 0.1989907
A8: Other intangible assets | B8: 2825 | C8: 2766 | D8: =(B8/C8)-1 -> 0.021330441
A9: Non-current investments | B9: 8930 | C9: 11059 | D9: =(B9/C9)-1 -> -0.19251289
A10: Non-current loans | B10: 6 | C10: 16 | D10: =(B10/C10)-1 -> -0.625
A11: Other non-current financial assets | B11: 2776 | C11: 3511 | D11: =(B11/C11)-1 -> -0.20934207
A12: Deferred tax assets | B12: 2264 | C12: 1108 | D12: =(B12/C12)-1 -> 1.0433213
A13: Income tax assets | B13: 666 | C13: 1622 | D13: =(B13/C13)-1 -> -0.58939581
A14: Other non-current assets | B14: 3540 | C14: 2713 | D14: =(B14/C14)-1 -> 0.3048286
A15: Total non-current assets | B15: 52478 | C15: 51804 | D15: =(B15/C15)-1 -> 0.013010578
... A22: Other current assets | B22: 15145 | C22: 11940 | D22: =(B22/C22)-1 -> 0.26842546
A23: Total current assets | B23: 103489 | C23: 97099 | D23: =(B23/C23)-1 -> 0.065809123 | I23: S
A24: Total assets | B24: 155967 | C24: 148903 | D24: =(B24/C24)-1 -> 0.04744028
A25: Equity share capital | B25: 2024 | C25: 2073 | D25: =(B25/C25)-1 -> -0.023637241
A26: Other equity | B26: 90828 | C26: 93745 | D26: =(B26/C26)-1 -> -0.031116326
A27: Non-controlling interests | B27: 445 | C27: 385 | D27: =(B27/C27)-1 -> 0.15584416
A28: Total equity | B28: 93297 | C28: 96203 | D28: =(B28/C28)-1 -> -0.030206958
A29: Non-current lease liabilities | B29: 6016 | C29: 5772 | D29: =(B29/C29)-1 -> 0.042273042
A30: Other non-current financial liabilities | B30: 2092 | C30: 2141 | D30: =(B30/C30)-1 -> -0.022886502
A31: Deferred tax liabilities | B31: 1679 | C31: 1722 | D31: =(B31/C31)-1 -> -0.024970964
A32: Other non-current liabilities | B32: 561 | C32: 215 | D32: =(B32/C32)-1 -> 1.6093023
A33: Total non-current liabilities | B33: 10348 | C33: 9850 | D33: =(B33/C33)-1 -> 0.050558376
A34: Current lease liabilities | B34: 3160 | C34: 2455 | D34: =(B34/C34)-1 -> 0.28716904
A35: Trade payables | B35: 4744 | C35: 4164 | D35: =(B35/C35)-1 -> 0.13928915
... A41: Total equity and liabilities | B41: 155967 | C41: 148903 | D41: =(B41/C41)-1 -> 0.04744028

Sheet Cash Flow Statement
A1: INFOSYS CONSOLIDATED CASH FLOW STATEMENT
A3: Particulars | B3: FY2026 | C3: FY2025 | D3: Growth %
A4: Cash flow from operating activities | B4: - | C4: -
A5: Profit for the year | B5: 29474 | C5: 26750 | D5: =IF(OR(C5="-",C5=0),"N/A",(B5/C5)-1) -> 0.10183178
A6: Income tax expense | B6: 10521 | C6: 10858 | D6: =IF(OR(C6="-",C6=0),"N/A",(B6/C6)-1) -> -0.031037023
A7: Depreciation and amortization | B7: 4902 | C7: 4812 | D7: =IF(OR(C7="-",C7=0),"N/A",(B7/C7)-1) -> 0.018703242
A8: Interest and dividend income | B8: -2630 | C8: -2570 | D8: =IF(OR(C8="-",C8=0),"N/A",(B8/C8)-1) -> 0.023346304
A9: Finance cost | B9: 416 | C9: 416 | D9: =IF(OR(C9="-",C9=0),"N/A",(B9/C9)-1) -> 0
A10: Impairment loss | B10: 33 | C10: 48 | D10: =IF(OR(C10="-",C10=0),"N/A",(B10/C10)-1) -> -0.3125
A11: Exchange differences | B11: 954 | C11: 79 | D11: =IF(OR(C11="-",C11=0),"N/A",(B11/C11)-1) -> 11.075949
A12: Stock compensation expense | B12: 952 | C12: 802 | D12: =IF(OR(C12="-",C12=0),"N/A",(B12/C12)-1) -> 0.18703242
A13: Interest receivable on income tax refund | B13: -63 | C13: -327 | D13: =IF(OR(C13="-",C13=0),"N/A",(B13/C13)-1) -> -0.80733945
A14: Provision for post-sale client support | B14: -167 | C14: -110 | D14: =IF(OR(C14="-",C14=0),"N/A",(B14/C14)-1) -> 0.51818182
A15: Other adjustments | B15: 881 | C15: 833 | D15: =IF(OR(C15="-",C15=0),"N/A",(B15/C15)-1) -> 0.057623049
A16: Changes in assets and liabilities | B16: - | C16: - | D16: =IF(OR(C16="-",C16=0),"N/A",(B16/C16)-1) -> N/A
A17: Trade receivables and unbilled revenue | B17: -5177 | C17: -1769 | D17: =IF(OR(C17="-",C17=0),"N/A",(B17/C17)-1) -> 1.9265122
A18: Loans, other financial assets and other assets | B18: -2645 | C18: -1024 | D18: =IF(OR(C18="-",C18=0),"N/A",(B18/C18)-1) -> 1.5830078
A19: Trade payables | B19: -26 | C19: 176 | D19: =IF(OR(C19="-",C19=0),"N/A",(B19/C19)-1) -> -1.1477273
A20: Other financial liabilities, other liabilities and provisions | B20: 5209 | C20: 2322 | D20: =IF(OR(C20="-",C20=0),"N/A",(B20/C20)-1) -> 1.2433247
A21: Cash generated from operations | B21: 42634 | C21: 41296 | D21: =IF(OR(C21="-",C21=0),"N/A",(B21/C21)-1) -> 0.032400232
A22: Income taxes paid | B22: -8648 | C22: -5602 | D22: =IF(OR(C22="-",C22=0),"N/A",(B22/C22)-1) -> 0.54373438
A23: Net cash generated by operating activities | B23: 33986 | C23: 35694 | D23: =IF(OR(C23="-",C23=0),"N/A",(B23/C23)-1) -> -0.047851179
A24: Cash flows from investing activities | B24: - | C24: - | D24: =IF(OR(C24="-",C24=0),"N/A",(B24/C24)-1) -> N/A
A25: Capital expenditure and intangibles | B25: -2727 | C25: -2237 | D25: =IF(OR(C25="-",C25=0),"N/A",(B25/C25)-1) -> 0.21904336
A26: Deposits placed with Corporation | B26: -944 | C26: -1225 | D26: =IF(OR(C26="-",C26=0),"N/A",(B26/C26)-1) -> -0.22938776
A27: Redemption of deposits | B27: 725 | C27: 776 | D27: =IF(OR(C27="-",C27=0),"N/A",(B27/C27)-1) -> -0.065721649
A28: Interest and dividend received | B28: 2713 | C28: 2040 | D28: =IF(OR(C28="-",C28=0),"N/A",(B28/C28)-1) -> 0.32990196
A29: Acquisition of business | B29: -637 | C29: -3155 | D29: =IF(OR(C29="-",C29=0),"N/A",(B29/C29)-1) -> -0.79809826
A30: Payment of contingent consideration | B30: -13 | C30: 0 | D30: =IF(OR(C30="-",C30=0),"N/A",(B30/C30)-1) -> N/A
A31: Escrow and other deposits pertaining to buyback | B31: -1815 | C31: 0 | D31: =IF(OR(C31="-",C31=0),"N/A",(B31/C31)-1) -> N/A
A32: Redemption of escrow and other deposits | B32: 1815 | C32: 0 | D32: =IF(OR(C32="-",C32=0),"N/A",(B32/C32)-1) -> N/A
A33: Other receipts | B33: 15 | C33: 10 | D33: =IF(OR(C33="-",C33=0),"N/A",(B33/C33)-1) -> 0.5
A34: Payments to acquire investments | B34: -96656 | C34: -89731 | D34: =IF(OR(C34="-",C34=0),"N/A",(B34/C34)-1) -> 0.077175112
A35: Proceeds on sale of investments | B35: 99470 | C35: 91576 | D35: =IF(OR(C35="-",C35=0),"N/A",(B35/C35)-1) -> 0.086201625
A36: Net cash generated / (used in) investing activities | B36: 1946 | C36: -1946 | D36: =IF(OR(C36="-",C36=0),"N/A",(B36/C36)-1) -> -2
A37: Cash flows from financing activities | B37: - | C37: - | D37: =IF(OR(C37="-",C37=0),"N/A",(B37/C37)-1) -> N/A
A38: Payment of lease liabilities | B38: -2824 | C38: -2824 | D38: =IF(OR(C38="-",C38=0),"N/A",(B38/C38)-1) -> 0
A39: Payment of dividends | B39: -18653 | C39: -20287 | D39: =IF(OR(C39="-",C39=0),"N/A",(B39/C39)-1) -> -0.080544191
A40: Loan repayment | B40: 0 | C40: -985 | D40: =IF(OR(C40="-",C40=0),"N/A",(B40/C40)-1) -> -1
A41: Dividend to non-controlling interest | B41: -3 | C41: -2 | D41: =IF(OR(C41="-",C41=0),"N/A",(B41/C41)-1) -> 0.5
A42: Shares issued on exercise of employee stock options | B42: 2 | C42: 6 | D42: =IF(OR(C42="-",C42=0),"N/A",(B42/C42)-1) -> -0.66666667
A43: Buyback of equity shares including transaction costs | B43: -18058 | C43: 0 | D43: =IF(OR(C43="-",C43=0),"N/A",(B43/C43)-1) -> N/A
A44: Other payments | B44: -250 | C44: -538 | D44: =IF(OR(C44="-",C44=0),"N/A",(B44/C44)-1) -> -0.53531599
A45: Net cash used in financing activities | B45: -39786 | C45: -24161 | D45: =IF(OR(C45="-",C45=0),"N/A",(B45/C45)-1) -> 0.64670336
A46: Net increase / (decrease) in cash and cash equivalents | B46: -3854 | C46: 9587 | D46: =IF(OR(C46="-",C46=0),"N/A",(B46/C46)-1) -> -1.4020027
A47: Effect of exchange rate changes | B47: 1600 | C47: 82 | D47: =IF(OR(C47="-",C47=0),"N/A",(B47/C47)-1) -> 18.512195
A48: Cash and cash equivalents at beginning of period | B48: 24455 | C48: 14786 | D48: =IF(OR(C48="-",C48=0),"N/A",(B48/C48)-1) -> 0.65392939
A49: Cash and cash equivalents at end of period | B49: 22201 | C49: 24455 | D49: =IF(OR(C49="-",C49=0),"N/A",(B49/C49)-1) -> -0.092169291

Sheet 3-Statement Model
A1: INFOSYS 3-STATEMENT FINANCIAL MODEL
A3: Particulars | B3: FY2026 | C3: FY2025 | D3: FY2027 | E3: FY2028 | F3: FY2029
A4: INCOME STATEMENT
A5: Revenue from operations | B5: ='Income Statement'!B4 -> 178650 | C5: ='Income Statement'!C4 -> 162990 | D5: =B5*(1+Assumptions!B4) -> 192942 | E5: =D5*(1+Assumptions!C4) -> 208377.36 | F5: =E5*(1+Assumptions!D4) -> 225047.55
A6: Other income | B6: ='Income Statement'!B5 -> 4322 | C6: ='Income Statement'!C5 -> 3600 | D6: =D5*Assumptions!B5 -> 4630.608 | E6: =E5*Assumptions!C5 -> 5001.0566 | F6: =F5*Assumptions!D5 -> 5401.1412
A7: Total income | B7: ='Income Statement'!B6 -> 182972 | C7: ='Income Statement'!C6 -> 166590 | D7: =D5+D6 -> 197572.61 | E7: =E5+E6 -> 213378.42 | F7: =F5+F6 -> 230448.69
A8: Employee benefit expenses | B8: ='Income Statement'!B7 -> 95094 | C8: ='Income Statement'!C7 -> 85950 | D8: =D5*Assumptions!B6 -> 102645.14 | E8: =E5*Assumptions!C6 -> 110856.76 | F8: =F5*Assumptions!D6 -> 119725.3
A9: Cost of technical sub-contractors | B9: ='Income Statement'!B8 -> 15421 | C9: ='Income Statement'!C8 -> 12937 | D9: =D5*($B$9/$B$5) -> 16654.68 | E9: =E5*($B$9/$B$5) -> 17987.054 | F9: =F5*($B$9/$B$5) -> 19426.019
A10: Travel expenses | B10: ='Income Statement'!B9 -> 2097 | C10: ='Income Statement'!C9 -> 1894 | D10: =D5*($B$10/$B$5) -> 2264.76 | E10: =E5*($B$10/$B$5) -> 2445.9408 | F10: =E5*($B$10/$B$5) -> 2445.9408
A11: Cost of software packages and others | B11: ='Income Statement'!B10 -> 15722 | C11: ='Income Statement'!C10 -> 15911 | D11: =D5*($B$11/$B$5) -> 16979.76 | E11: =E5*($B$11/$B$5) -> 18338.141 | F11: =F5*($B$11/$B$5) -> 19805.192
A12: Communication expenses | B12: ='Income Statement'!B11 -> 603 | C12: ='Income Statement'!C11 -> 620 | D12: =D5*($B$12/$B$5) -> 651.24 | E12: =E5*($B$12/$B$5) -> 703.3392 | F12: =F5*($B$12/$B$5) -> 759.60634
A13: Consultancy and professional charges | B13: ='Income Statement'!B12 -> 2090 | C13: ='Income Statement'!C12 -> 1655 | D13: =D5*($B$13/$B$5) -> 2257.2 | E13: =E5*($B$13/$B$5) -> 2437.776 | F13: =F5*($B$13/$B$5) -> 2632.7981
A14: Depreciation and amortization expenses | B14: ='Income Statement'!B13 -> 4902 | C14: ='Income Statement'!C13 -> 4812 | D14: =D5*Assumptions!B8 -> 5209.434 | E14: =E5*Assumptions!C8 -> 5626.1887 | F14: =F5*Assumptions!D8 -> 6076.2838
A15: Finance cost | B15: ='Income Statement'!B14 -> 416 | C15: ='Income Statement'!C14 -> 416 | D15: =D5*Assumptions!B9 -> 385.884 | E15: =E5*Assumptions!C9 -> 416.75472 | F15: =F5*Assumptions!D9 -> 450.0951
A16: Other expenses | B16: ='Income Statement'!B15 -> 5343 | C16: ='Income Statement'!C15 -> 4787 | D16: =D5*($B$16/$B$5) -> 5770.44 | E16: =E5*($B$16/$B$5) -> 6232.0752 | F16: =F5*($B$16/$B$5) -> 6730.6412
A17: Total expenses | B17: ='Income Statement'!B16 -> 141688 | C17: ='Income Statement'!C16 -> 128982 | D17: =SUM(D8:D16) -> 152818.54 | E17: =SUM(E8:E16) -> 165044.03 | F17: =SUM(F8:F16) -> 178051.87
A18: Profit before exceptional item and tax | B18: ='Income Statement'!B17 -> 41284 | C18: ='Income Statement'!C17 -> 37608 | D18: =D7-D17 -> 44754.066 | E18: =E7-E17 -> 48334.391 | F18: =F7-F17 -> 52396.818
A19: Exceptional item | B19: ='Income Statement'!B18 -> 1289 | C19: ='Income Statement'!C18 -> 0 | D19: =0 -> 0 | E19: =0 -> 0 | F19: =0 -> 0
A20: Profit before tax | B20: ='Income Statement'!B19 -> 39995 | C20: ='Income Statement'!C19 -> 37608 | D20: =D18+D19 -> 44754.066 | E20: =E18+E19 -> 48334.391 | F20: =F18+F19 -> 52396.818
A21: Current tax | B21: ='Income Statement'!B20 -> 11767 | C21: ='Income Statement'!C20 -> 12130 | D21: =D20*Assumptions!B10 -> 11770.319 | E21: =E20*Assumptions!C10 -> 12711.945 | F21: =F20*Assumptions!D10 -> 13780.363
A22: Deferred tax | B22: ='Income Statement'!B21 -> -1246 | C22: ='Income Statement'!C21 -> -1272 | D22: =0 -> 0 | E22: =0 -> 0 | F22: =0 -> 0
A23: Profit for the year | B23: ='Income Statement'!B22 -> 29474 | C23: ='Income Statement'!C22 -> 26750 | D23: =D20-D21+D22 -> 32983.747 | E23: =E20-E21+E22 -> 35622.446 | F23: =F20-F21+F22 -> 38616.455
A25: BALANCE SHEET
A26: Property, plant and equipment | B26: ='Balance Sheet'!B4 -> 12651 | C26: ='Balance Sheet'!C4 -> 11778 | D26: =B26-D87-D14 -> 10335.696 | E26: =C26-E87-E14 -> 9277.4717 | F26: =D26-F87-F14 -> 7635.1254
A27: Right-of-use assets | B27: ='Balance Sheet'!B5 -> 6177 | C27: ='Balance Sheet'!C5 -> 6311 | D27: =D5*($B$27/$B$5) -> 6671.16 | E27: =E5*($B$27/$B$5) -> 7204.8528 | F27: =F5*($B$27/$B$5) -> 7781.241
A28: Capital work-in-progress | B28: ='Balance Sheet'!B6 -> 526 | C28: ='Balance Sheet'!C6 -> 814 | D28: =D5*($B$28/$B$5) -> 568.08 | E28: =E5*($B$28/$B$5) -> 613.5264 | F28: =F5*($B$28/$B$5) -> 662.60851
A29: Goodwill | B29: ='Balance Sheet'!B7 -> 12117 | C29: ='Balance Sheet'!C7 -> 10106 | D29: =D5*($B$29/$B$5) -> 13086.36 | E29: =E5*($B$29/$B$5) -> 14133.269 | F29: =F5*($B$29/$B$5) -> 15263.93
A30: Other intangible assets | B30: ='Balance Sheet'!B8 -> 2825 | C30: ='Balance Sheet'!C8 -> 2766 | D30: =D5*($B$30/$B$5) -> 3051 | E30: =E5*($B$30/$B$5) -> 3295.08 | F30: =F5*($B$30/$B$5) -> 3558.6864
A31: Non-current investments | B31: ='Balance Sheet'!B9 -> 8930 | C31: ='Balance Sheet'!C9 -> 11059 | D31: =D5*($B$31/$B$5) -> 9644.4 | E31: =E5*($B$31/$B$5) -> 10415.952 | F31: =F5*($B$31/$B$5) -> 11249.228
A32: Non-current loans | B32: ='Balance Sheet'!B10 -> 6 | C32: ='Balance Sheet'!C10 -> 16 | D32: =D5*($B$32/$B$5) -> 6.48 | E32: =E5*($B$32/$B$5) -> 6.9984 | F32: =F5*($B$32/$B$5) -> 7.558272
A33: Other non-current financial assets | B33: ='Balance Sheet'!B11 -> 2776 | C33: ='Balance Sheet'!C11 -> 3511 | D33: =D5*($B$33/$B$5) -> 2998.08 | E33: =E5*($B$33/$B$5) -> 3237.9264 | F33: =F5*($B$33/$B$5) -> 3496.9605
A34: Deferred tax assets | B34: ='Balance Sheet'!B12 -> 2264 | C34: ='Balance Sheet'!C12 -> 1108 | D34: =D5*($B$34/$B$5) -> 2445.12 | E34: =E5*($B$34/$B$5) -> 2640.7296 | F34: =F5*($B$34/$B$5) -> 2851.988
A35: Income tax assets | B35: ='Balance Sheet'!B13 -> 666 | C35: ='Balance Sheet'!C13 -> 1622 | D35: =D5*($B$35/$B$5) -> 719.28 | E35: =E5*($B$35/$B$5) -> 776.8224 | F35: =F5*($B$35/$B$5) -> 838.96819
A36: Other non-current assets | B36: ='Balance Sheet'!B14 -> 3540 | C36: ='Balance Sheet'!C14 -> 2713 | D36: =D5*($B$36/$B$5) -> 3823.2 | E36: =E5*($B$36/$B$5) -> 4129.056 | F36: =F5*($B$36/$B$5) -> 4459.3805
A37: Total non-current assets | B37: ='Balance Sheet'!B15 -> 52478 | C37: ='Balance Sheet'!C15 -> 51804 | D37: =SUM(D26:D36) -> 53348.856 | E37: =SUM(E26:E36) -> 55731.684 | F37: =SUM(F26:F36) -> 57805.675
A38: Current investments | B38: ='Balance Sheet'!B16 -> 12950 | C38: ='Balance Sheet'!C16 -> 12482 | D38: =D5*($B$38/$B$5) -> 13986 | E38: =E5*($B$38/$B$5) -> 15104.88 | F38: =F5*($B$38/$B$5) -> 16313.27
A39: Trade receivables | B39: ='Balance Sheet'!B17 -> 35234 | C39: ='Balance Sheet'!C17 -> 31158 | D39: =D5*Assumptions!B12 -> 38009.574 | E39: =E5*Assumptions!C12 -> 41050.34 | F39: =F5*Assumptions!D12 -> 44334.367
A40: Cash and cash equivalents | B40: ='Balance Sheet'!B18 -> 22201 | C40: ='Balance Sheet'!C18 -> 24455 | D40: =D111 -> 32173.75 | E40: =E111 -> 32074.97 | F40: =F111 -> 38680.617
A41: Current loans | B41: ='Balance Sheet'!B19 -> 234 | C41: ='Balance Sheet'!C19 -> 249 | D41: =D5*($B$41/$B$5) -> 252.72 | E41: =E5*($B$41/$B$5) -> 272.9376 | F41: =F5*($B$41/$B$5) -> 294.77261
A42: Other current financial assets | B42: ='Balance Sheet'!B20 -> 15890 | C42: ='Balance Sheet'!C20 -> 13840 | D42: =D5*($B$42/$B$5) -> 17161.2 | E42: =E5*($B$42/$B$5) -> 18534.096 | F42: =F5*($B$42/$B$5) -> 20016.824
A43: Current income tax assets | B43: ='Balance Sheet'!B21 -> 1835 | C43: ='Balance Sheet'!C21 -> 2975 | D43: =D5*($B$43/$B$5) -> 1981.8 | E43: =E5*($B$43/$B$5) -> 2140.344 | F43: =F5*($B$43/$B$5) -> 2311.5715
A44: Other current assets | B44: ='Balance Sheet'!B22 -> 15145 | C44: ='Balance Sheet'!C22 -> 11940 | D44: =D5*($B$44/$B$5) -> 16356.6 | E44: =E5*($B$44/$B$5) -> 17665.128 | F44: =F5*($B$44/$B$5) -> 19078.338
A45: Total current assets | B45: ='Balance Sheet'!B23 -> 103489 | C45: ='Balance Sheet'!C23 -> 97099 | D45: =SUM(D38:D44) -> 119921.64 | E45: =SUM(E38:E44) -> 126842.7 | F45: =SUM(F38:F44) -> 141029.76
A46: Total assets | B46: ='Balance Sheet'!B24 -> 155967 | C46: ='Balance Sheet'!C24 -> 148903 | D46: =D37+D45 -> 173270.5 | E46: =E37+E45 -> 182574.38 | F46: =F37+F45 -> 198835.44
A47: Equity share capital | B47: ='Balance Sheet'!B25 -> 2024 | C47: ='Balance Sheet'!C25 -> 2073 | D47: =B47 -> 2024 | E47: =C47 -> 2073 | F47: =D47 -> 2024
A48: Other equity | B48: ='Balance Sheet'!B26 -> 90828 | C48: ='Balance Sheet'!C26 -> 93745 | D48: =B48+D23-(D23*Assumptions!B14) -> 103031.99 | E48: =C48+E23-(E23*Assumptions!C14) -> 106925.31 | F48: =D48+F23-(F23*Assumptions!D14) -> 117320.07
A49: Non-controlling interests | B49: ='Balance Sheet'!B27 -> 445 | C49: ='Balance Sheet'!C27 -> 385 | D49: =B49 -> 445 | E49: =C49 -> 385 | F49: =D49 -> 445
A50: Total equity | B50: ='Balance Sheet'!B28 -> 93297 | C50: ='Balance Sheet'!C28 -> 96203 | D50: =SUM(D47:D49) -> 105500.99 | E50: =SUM(E47:E49) -> 109383.31 | F50: =SUM(F47:F49) -> 119789.07
A51: Non-current lease liabilities | B51: ='Balance Sheet'!B29 -> 6016 | C51: ='Balance Sheet'!C29 -> 5772 | D51: =D5*($B$51/$B$5) -> 6497.28 | E51: =E5*($B$51/$B$5) -> 7017.0624 | F51: =F5*($B$51/$B$5) -> 7578.4274
A52: Other non-current financial liabilities | B52: ='Balance Sheet'!B30 -> 2092 | C52: ='Balance Sheet'!C30 -> 2141 | D52: =D5*($B$52/$B$5) -> 2259.36 | E52: =E5*($B$52/$B$5) -> 2440.1088 | F52: =F5*($B$52/$B$5) -> 2635.3175
A53: Deferred tax liabilities | B53: ='Balance Sheet'!B31 -> 1679 | C53: ='Balance Sheet'!C31 -> 1722 | D53: =D5*($B$53/$B$5) -> 1813.32 | E53: =E5*($B$53/$B$5) -> 1958.3856 | F53: =F5*($B$53/$B$5) -> 2115.0564
A54: Other non-current liabilities | B54: ='Balance Sheet'!B32 -> 561 | C54: ='Balance Sheet'!C32 -> 215 | D54: =D5*($B$54/$B$5) -> 605.88 | E54: =E5*($B$54/$B$5) -> 654.3504 | F54: =F5*($B$54/$B$5) -> 706.69843
A55: Total non-current liabilities | B55: ='Balance Sheet'!B33 -> 10348 | C55: ='Balance Sheet'!C33 -> 9850 | D55: =SUM(D51:D54) -> 11175.84 | E55: =SUM(E51:E54) -> 12069.907 | F55: =SUM(F51:F54) -> 13035.5
A56: Current lease liabilities | B56: ='Balance Sheet'!B34 -> 3160 | C56: ='Balance Sheet'!C34 -> 2455 | D56: =D5*($B$56/$B$5) -> 3412.8 | E56: =E5*($B$56/$B$5) -> 3685.824 | F56: =F5*($B$56/$B$5) -> 3980.6899
A57: Trade payables | B57: ='Balance Sheet'!B35 -> 4744 | C57: ='Balance Sheet'!C35 -> 4164 | D57: =D5*Assumptions!B13 -> 5209.434 | E57: =E5*Assumptions!C13 -> 5626.1887 | F57: =F5*Assumptions!D13 -> 6076.2838
A58: Other current financial liabilities | B58: ='Balance Sheet'!B36 -> 21483 | C58: ='Balance Sheet'!C36 -> 18138 | D58: =D5*($B$58/$B$5) -> 23201.64 | E58: =E5*($B$58/$B$5) -> 25057.771 | F58: =F5*($B$58/$B$5) -> 27062.393
A59: Other current liabilities | B59: ='Balance Sheet'!B37 -> 15779 | C59: ='Balance Sheet'!C37 -> 11765 | D59: =D5*($B$59/$B$5) -> 17041.32 | E59: =E5*($B$59/$B$5) -> 18404.626 | F59: =F5*($B$59/$B$5) -> 19876.996
A60: Provisions | B60: ='Balance Sheet'!B38 -> 1512 | C60: ='Balance Sheet'!C38 -> 1475 | D60: =D5*($B$60/$B$5) -> 1632.96 | E60: =E5*($B$60/$B$5) -> 1763.5968 | F60: =F5*($B$60/$B$5) -> 1904.6845
A61: Income tax liabilities | B61: ='Balance Sheet'!B39 -> 5644 | C61: ='Balance Sheet'!C39 -> 4853 | D61: =D5*($B$61/$B$5) -> 6095.52 | E61: =E5*($B$61/$B$5) -> 6583.1616 | F61: =F5*($B$61/$B$5) -> 7109.8145
A62: Total current liabilities | B62: ='Balance Sheet'!B40 -> 52322 | C62: ='Balance Sheet'!C40 -> 42850 | D62: =SUM(D56:D61) -> 56593.674 | E62: =SUM(E56:E61) -> 61121.168 | F62: =SUM(F56:F61) -> 66010.861
A63: Total equity and liabilities | B63: ='Balance Sheet'!B41 -> 155967 | C63: ='Balance Sheet'!C41 -> 148903 | D63: =D50+D55+D62 -> 173270.5 | E63: =E50+E55+E62 -> 182574.38 | F63: =F50+F55+F62 -> 198835.44
A65: CASH FLOW STATEMENT
A66: Cash flow from operating activities
A67: Profit for the year | B67: ='Cash Flow Statement'!B5 -> 29474 | C67: ='Cash Flow Statement'!C5 -> 26750 | D67: =D23 -> 32983.747 | E67: =E23 -> 35622.446 | F67: =F23 -> 38616.455
A68: Income tax expense | B68: ='Cash Flow Statement'!B6 -> 10521 | C68: ='Cash Flow Statement'!C6 -> 10858 | D68: =D21+D22 -> 11770.319 | E68: =E21+E22 -> 12711.945 | F68: =F21+F22 -> 13780.363
A69: Depreciation and amortization | B69: ='Cash Flow Statement'!B7 -> 4902 | C69: ='Cash Flow Statement'!C7 -> 4812 | D69: =D14 -> 5209.434 | E69: =E14 -> 5626.1887 | F69: =F14 -> 6076.2838
A70: Interest and dividend income | B70: ='Cash Flow Statement'!B8 -> -2630 | C70: ='Cash Flow Statement'!C8 -> -2570 | D70: =D5*($B$70/$B$5) -> -2840.4 | E70: =E5*($B$70/$B$5) -> -3067.632 | F70: =F5*($B$70/$B$5) -> -3313.0426
A71: Finance cost | B71: ='Cash Flow Statement'!B9 -> 416 | C71: ='Cash Flow Statement'!C9 -> 416 | D71: =D15 -> 385.884 | E71: =E15 -> 416.75472 | F71: =F15 -> 450.0951
A72: Impairment loss | B72: ='Cash Flow Statement'!B10 -> 33 | C72: ='Cash Flow Statement'!C10 -> 48 | D72: =D5*($B$72/$B$5) -> 35.64 | E72: =E5*($B$72/$B$5) -> 38.4912 | F72: =F5*($B$72/$B$5) -> 41.570496
A73: Exchange differences | B73: ='Cash Flow Statement'!B11 -> 954 | C73: ='Cash Flow Statement'!C11 -> 79 | D73: =D5*($B$73/$B$5) -> 1030.32 | E73: =E5*($B$73/$B$5) -> 1112.7456 | F73: =F5*($B$73/$B$5) -> 1201.7652
A74: Stock compensation expense | B74: ='Cash Flow Statement'!B12 -> 952 | C74: ='Cash Flow Statement'!C12 -> 802 | D74: =D5*($B$74/$B$5) -> 1028.16 | E74: =E5*($B$74/$B$5) -> 1110.4128 | F74: =F5*($B$74/$B$5) -> 1199.2458
A75: Interest receivable on income tax refund | B75: ='Cash Flow Statement'!B13 -> -63 | C75: ='Cash Flow Statement'!C13 -> -327 | D75: =D5*($B$75/$B$5) -> -68.04 | E75: =E5*($B$75/$B$5) -> -73.4832 | F75: =F5*($B$75/$B$5) -> -79.361856
A76: Provision for post-sale client support | B76: ='Cash Flow Statement'!B14 -> -167 | C76: ='Cash Flow Statement'!C14 -> -110 | D76: =D5*($B$76/$B$5) -> -180.36 | E76: =E5*($B$76/$B$5) -> -194.7888 | F76: =F5*($B$76/$B$5) -> -210.3719
A77: Other adjustments / BS reconciliation | B77: ='Cash Flow Statement'!B15 -> 881 | C77: ='Cash Flow Statement'!C15 -> 833 | D77: =(D63-(D37+D38+D39+D41+D42+D43+D44)-B40)-(SUM(D67:D76)+SUM(D79:D82)+D84+D98+D107+D109) -> -2481.934 | E77: =(E63-(E37+E38+E39+E41+E42+E43+E44)-D40)-(SUM(E67:E76)+SUM(E79:E82)+E84+E98+E107+E109) -> -13026.599 | F77: =(F63-(F37+F38+F39+F41+F42+F43+F44)-E40)-(SUM(F67:F76)+SUM(F79:F82)+F84+F98+F107+F109) -> -4536.9382
A78: Changes in assets and liabilities | B78: ='Cash Flow Statement'!B16 -> - | C78: ='Cash Flow Statement'!C16 -> - | D78: - | E78: - | F78: -
A79: Trade receivables and unbilled revenue | B79: ='Cash Flow Statement'!B17 -> -5177 | C79: ='Cash Flow Statement'!C17 -> -1769 | D79: =-(D39-B39) -> -2775.574 | E79: =-(E39-C39) -> -9892.3399 | F79: =-(F39-D39) -> -6324.7931
A80: Loans, other financial assets and other assets | B80: ='Cash Flow Statement'!B18 -> -2645 | C80: ='Cash Flow Statement'!C18 -> -1024 | D80: =-((D41+D42+D43+D44)-(B41+B42+B43+B44)) -> -2648.32 | E80: =-((E41+E42+E43+E44)-(C41+C42+C43+C44)) -> -9608.5056 | F80: =-((F41+F42+F43+F44)-(D41+D42+D43+D44)) -> -5949.186
A81: Trade payables | B81: ='Cash Flow Statement'!B19 -> -26 | C81: ='Cash Flow Statement'!C19 -> 176 | D81: =D57-B57 -> 465.434 | E81: =E57-C57 -> 1462.1887 | F81: =F57-D57 -> 866.84982
A82: Other financial liabilities, other liabilities and provisions | B82: ='Cash Flow Statement'!B20 -> 5209 | C82: ='Cash Flow Statement'!C20 -> 2322 | D82: =(D52+D54+D58+D59+D60+D61)-(B52+B54+B58+B59+B60+B61) -> 3765.68 | E82: =(E52+E54+E58+E59+E60+E61)-(C52+C54+C58+C59+C60+C61) -> 16316.614 | F82: =(F52+F54+F58+F59+F60+F61)-(D52+D54+D58+D59+D60+D61) -> 8459.2236
A83: Cash generated from operations | B83: ='Cash Flow Statement'!B21 -> 42634 | C83: ='Cash Flow Statement'!C21 -> 41296 | D83: =SUM(D67:D82) -> 45679.99 | E83: =SUM(E67:E82) -> 38554.439 | F83: =SUM(F67:F82) -> 50278.158
A84: Income taxes paid | B84: ='Cash Flow Statement'!B22 -> -8648 | C84: ='Cash Flow Statement'!C22 -> -5602 | D84: =D68*($B$84/$B$68) -> -9674.9094 | E84: =E68*($B$84/$B$68) -> -10448.902 | F84: =F68*($B$84/$B$68) -> -11327.115
A85: Net cash generated by operating activities | B85: ='Cash Flow Statement'!B23 -> 33986 | C85: ='Cash Flow Statement'!C23 -> 35694 | D85: =D83+D84 -> 36005.081 | E85: =E83+E84 -> 28105.537 | F85: =F83+F84 -> 38951.043
A86: Cash flows from investing activities | B86: ='Cash Flow Statement'!B24 -> - | C86: ='Cash Flow Statement'!C24 -> - | D86: - | E86: - | F86: -
A87: Expenditure on property, plant and equipment and intangibles | B87: ='Cash Flow Statement'!B25 -> -2727 | C87: ='Cash Flow Statement'!C25 -> -2237 | D87: =-D5*Assumptions!B11 -> -2894.13 | E87: =-E5*Assumptions!C11 -> -3125.6604 | F87: =-F5*Assumptions!D11 -> -3375.7132
A88: Deposits placed with Corporation | B88: ='Cash Flow Statement'!B26 -> -944 | C88: ='Cash Flow Statement'!C26 -> -1225 | D88: =D5*($B$88/$B$5) -> -1019.52 | E88: =E5*($B$88/$B$5) -> -1101.0816 | F88: =F5*($B$88/$B$5) -> -1189.1681
A89: Redemption of deposits | B89: ='Cash Flow Statement'!B27 -> 725 | C89: ='Cash Flow Statement'!C27 -> 776 | D89: =D5*($B$89/$B$5) -> 783 | E89: =E5*($B$89/$B$5) -> 845.64 | F89: =F5*($B$89/$B$5) -> 913.2912
A90: Interest and dividend received | B90: ='Cash Flow Statement'!B28 -> 2713 | C90: ='Cash Flow Statement'!C28 -> 2040 | D90: =D5*($B$90/$B$5) -> 2930.04 | E90: =E5*($B$90/$B$5) -> 3164.4432 | F90: =F5*($B$90/$B$5) -> 3417.5987
A91: Payment towards acquisition of business | B91: ='Cash Flow Statement'!B29 -> -637 | C91: ='Cash Flow Statement'!C29 -> -3155 | D91: =0 -> 0 | E91: =0 -> 0 | F91: =0 -> 0
A92: Payment of contingent consideration | B92: ='Cash Flow Statement'!B30 -> -13 | C92: ='Cash Flow Statement'!C30 -> 0 | D92: =0 -> 0 | E92: =0 -> 0 | F92: =0 -> 0
A93: Escrow and other deposits pertaining to buyback | B93: ='Cash Flow Statement'!B31 -> -1815 | C93: ='Cash Flow Statement'!C31 -> 0 | D93: =0 -> 0 | E93: =0 -> 0 | F93: =0 -> 0
A94: Redemption of escrow and other deposits | B94: ='Cash Flow Statement'!B32 -> 1815 | C94: ='Cash Flow Statement'!C32 -> 0 | D94: =0 -> 0 | E94: =0 -> 0 | F94: =0 -> 0
A95: Other receipts | B95: ='Cash Flow Statement'!B33 -> 15 | C95: ='Cash Flow Statement'!C33 -> 10 | D95: =D5*($B$95/$B$5) -> 16.2 | E95: =E5*($B$95/$B$5) -> 17.496 | F95: =F5*($B$95/$B$5) -> 18.89568
A96: Payments to acquire investments | B96: ='Cash Flow Statement'!B34 -> -96656 | C96: ='Cash Flow Statement'!C34 -> -89731 | D96: =-MAX(0,(D31+D38)-(B31+B38)) -> -1750.4 | E96: =-MAX(0,(E31+E38)-(C31+C38)) -> -1979.832 | F96: =-MAX(0,(F31+F38)-(D31+D38)) -> -3932.0986
A97: Proceeds on sale of investments | B97: ='Cash Flow Statement'!B35 -> 99470 | C97: ='Cash Flow Statement'!C35 -> 91576 | D97: =MAX(0,(B31+B38)-(D31+D38)) -> 0 | E97: =MAX(0,(C31+C38)-(E31+E38)) -> 0 | F97: =MAX(0,(D31+D38)-(F31+F38)) -> 0
A98: Net cash generated/(used in) from investing activities | B98: ='Cash Flow Statement'!B36 -> 1946 | C98: ='Cash Flow Statement'!C36 -> -1946 | D98: =SUM(D87:D97) -> -1934.81 | E98: =SUM(E87:E97) -> -2178.9948 | F98: =SUM(F87:F97) -> -4147.1944
A99: Cash flows from financing activities | B99: ='Cash Flow Statement'!B37 -> - | C99: ='Cash Flow Statement'!C37 -> - | D99: - | E99: - | F99: -
A100: Payment of lease liabilities | B100: ='Cash Flow Statement'!B38 -> -2824 | C100: ='Cash Flow Statement'!C38 -> -2824 | D100: =D5*($B$100/$B$5) -> -3049.92 | E100: =E5*($B$100/$B$5) -> -3293.9136 | F100: =F5*($B$100/$B$5) -> -3557.4267
A101: Payment of dividends | B101: ='Cash Flow Statement'!B39 -> -18653 | C101: ='Cash Flow Statement'!C39 -> -20287 | D101: =-D23*Assumptions!B14 -> -20779.76 | E101: =-E23*Assumptions!C14 -> -22442.141 | F101: =-F23*Assumptions!D14 -> -24328.366
A102: Loan repayment | B102: ='Cash Flow Statement'!B40 -> 0 | C102: ='Cash Flow Statement'!C40 -> -985 | D102: =0 -> 0 | E102: =0 -> 0 | F102: =0 -> 0
A103: Dividend to non-controlling interest | B103: ='Cash Flow Statement'!B41 -> -3 | C103: ='Cash Flow Statement'!C41 -> -2 | D103: =0 -> 0 | E103: =0 -> 0 | F103: =0 -> 0
...

Sheet Analysis
A1: INFOSYS FINANCIAL ANALYSIS
A3: Metric | B3: FY2026 | C3: FY2027 | D3: FY2028 | E3: FY2029
A4: Revenue Growth | B4: ='3-Statement Model'!B5/'3-Statement Model'!C5-1 -> 0.096079514 | C4: ='3-Statement Model'!D5/'3-Statement Model'!B5-1 -> 0.08 | D4: ='3-Statement Model'!E5/'3-Statement Model'!D5-1 -> 0.08 | E4: ='3-Statement Model'!F5/'3-Statement Model'!E5-1 -> 0.08
A5: Net Profit Margin | B5: ='3-Statement Model'!B23/'3-Statement Model'!B5 -> 0.16498181 | C5: ='3-Statement Model'!D23/'3-Statement Model'!D5 -> 0.17095162 | D5: ='3-Statement Model'!D23/'3-Statement Model'!D5 -> 0.17095162 | E5: ='3-Statement Model'!F23/'3-Statement Model'!F5 -> 0.17159243
A6: Operating Margin | B6: ='3-Statement Model'!B18/'3-Statement Model'!B5 -> 0.23108872 | C6: ='3-Statement Model'!D18/'3-Statement Model'!D5 -> 0.23195606 | D6: ='3-Statement Model'!E18/'3-Statement Model'!E5 -> 0.23195606 | E6: ='3-Statement Model'!F18/'3-Statement Model'!F5 -> 0.23282554
A7: ROE | B7: ='3-Statement Model'!B23/'3-Statement Model'!B50 -> 0.31591584 | C7: ='3-Statement Model'!D23/'3-Statement Model'!D50 -> 0.31263923 | D7: ='3-Statement Model'!E23/'3-Statement Model'!E50 -> 0.32566621 | E7: ='3-Statement Model'!F23/'3-Statement Model'!F50 -> 0.32237042
A8: ROA | B8: ='3-Statement Model'!B23/'3-Statement Model'!B46 -> 0.18897587 | C8: ='3-Statement Model'!D23/'3-Statement Model'!D46 -> 0.19035985 | D8: ='3-Statement Model'!E23/'3-Statement Model'!E46 -> 0.19511197 | E8: ='3-Statement Model'!F23/'3-Statement Model'!F46 -> 0.19421314
A9: Current Ratio | B9: ='3-Statement Model'!B45/'3-Statement Model'!B62 -> 1.9779252 | C9: ='3-Statement Model'!D45/'3-Statement Model'!D62 -> 2.1189938 | D9: ='3-Statement Model'!E45/'3-Statement Model'!E62 -> 2.0752662 | E9: ='3-Statement Model'!F45/'3-Statement Model'!F62 -> 2.136463
A10: Debt-to-Equity | B10: =('3-Statement Model'!B51+'3-Statement Model'!B56)/'3-Statement Model'!B50 -> 0.098352573 | C10: =('3-Statement Model'!D51+'3-Statement Model'!D56)/'3-Statement Model'!D50 -> 0.093933529 | D10: =('3-Statement Model'!E51+'3-Statement Model'!E56)/'3-Statement Model'!E50 -> 0.097847532 | E10: =('3-Statement Model'!F51+'3-Statement Model'!F56)/'3-Statement Model'!F50 -> 0.096495589
A11: CFO / Net Profit | B11: ='3-Statement Model'!B85/'3-Statement Model'!B23 -> 1.1530841 | C11: ='3-Statement Model'!D85/'3-Statement Model'!D23 -> 1.0916007 | D11: ='3-Statement Model'!E85/'3-Statement Model'!E23 -> 0.7889839 | E11: ='3-Statement Model'!F85/'3-Statement Model'!F23 -> 1.0086644
A12: Free Cash Flow | B12: ='3-Statement Model'!B85+'3-Statement Model'!B87 -> 31259 | C12: ='3-Statement Model'!D85+'3-Statement Model'!D87 -> 33110.951 | D12: ='3-Statement Model'!E85+'3-Statement Model'!E87 -> 24979.876 | E12: ='3-Statement Model'!F85+'3-Statement Model'!F87 -> 35575.329
A13: FCF Margin | B13: =B12/'3-Statement Model'!B5 -> 0.17497341 | C13: =C12/'3-Statement Model'!D5 -> 0.1716109 | D13: =D12/'3-Statement Model'!E5 -> 0.11987807 | E13: =E12/'3-Statement Model'!F5 -> 0.15807917
A14: Dividend Payout Ratio | B14: =-'3-Statement Model'!B101/'3-Statement Model'!B23 -> 0.63286286 | C14: =Assumptions!B14 -> 0.63 | D14: =Assumptions!C14 -> 0.63 | E14: =Assumptions!D14 -> 0.63
A15: Ending Cash | B15: ='3-Statement Model'!B111 -> 22201 | C15: ='3-Statement Model'!D111 -> 32173.75 | D15: ='3-Statement Model'!E111 -> 32074.97 | E15: ='3-Statement Model'!F111 -> 38680.617
A18: KEY MODEL CHECKS
A20: Balance Sheet Check | B20: ='3-Statement Model'!B63-'3-Statement Model'!B46 -> 0 | C20: ='3-Statement Model'!D63-'3-Statement Model'!D46 -> 0 | D20: ='3-Statement Model'!E63-'3-Statement Model'!E46 -> 0 | E20: ='3-Statement Model'!F63-'3-Statement Model'!F46 -> 0
A21: Cash Flow Check | B21: ='3-Statement Model'!B111-'3-Statement Model'!B40 -> 0 | C21: ='3-Statement Model'!C111-'3-Statement Model'!C40 -> 0 | D21: ='3-Statement Model'!D111-'3-Statement Model'!D40 -> 0 | E21: ='3-Statement Model'!E111-'3-Statement Model'!E40 -> 0
A22: Forecast Revenue Growth Check | B22: ='3-Statement Model'!B5/'3-Statement Model'!C5-1 -> 0.096079514 | C22: ='3-Statement Model'!D5/'3-Statement Model'!B5-1 -> 0.08 | D22: ='3-Statement Model'!E5/'3-Statement Model'!D5-1 -> 0.08 | E22: ='3-Statement Model'!F5/'3-Statement Model'!E5-1 -> 0.08
A23: Forecast Dividend Payout Check | B23: =-'3-Statement Model'!B101/'3-Statement Model'!B23 -> 0.63286286 | C23: =Assumptions!B14 -> 0.63 | D23: =-'3-Statement Model'!D101/'3-Statement Model'!D23 -> 0.63 | E23: =Assumptions!D14 -> 0.63
A26: MODEL INTERPRETATION
A27: 1. Revenue is forecast to grow at 8% annually from FY2027 to FY2029.
A28: 2. Net profit margin remains around 17% throughout the forecast period.
A29: 3. Operating margin remains broadly stable at approximately 23%.
A30: 4. Current ratio remains above 2.0x across the forecast period.
A31: 5. Free cash flow remains positive, while ending cash increases from ₹22,201 crore in FY2026 to ₹38,681 crore in FY2029.
A34: CHART SUPPORTING DATA
A35: Metric | B35: FY2026 | C35: FY2027 | D35: FY2028 | E35: FY2029
A36: Free Cash Flow | B36: 31259 | C36: 33111 | D36: 24980 | E36: 35575
A37: Ending Cash | B37: 22201 | C37: 32174 | D37: 32075 | E37: 38681
